videosdk/plugins/google/__init__.py
videosdk/plugins/google/live_api.py
videosdk/plugins/google/llm.py
videosdk/plugins/google/stt.py
videosdk/plugins/google/tts.py
videosdk/plugins/google/version.py
videosdk_plugins_google-0.0.58.dist-info/METADATA
videosdk_plugins_google-0.0.58.dist-info/WHEEL
videosdk_plugins_google-0.0.58.dist-info/RECORD
